hackathonbaobab2020/__init__.py
hackathonbaobab2020/main.py
hackathonbaobab2020/core/__init__.py
hackathonbaobab2020/core/batch.py
hackathonbaobab2020/core/experiment.py
hackathonbaobab2020/core/instance.py
hackathonbaobab2020/core/solution.py
hackathonbaobab2020/core/tools.py
hackathonbaobab2020/data/c15.mm.zip
hackathonbaobab2020/data/j10.mm.zip
hackathonbaobab2020/execution/__init__.py
hackathonbaobab2020/execution/benchmark.py
hackathonbaobab2020/execution/run_batch.py
hackathonbaobab2020/execution/test_script.py
hackathonbaobab2020/schemas/__init__.py
hackathonbaobab2020/schemas/config.json
hackathonbaobab2020/schemas/instance.json
hackathonbaobab2020/schemas/solution.json
hackathonbaobab2020/schemas/solution_checks.json
hackathonbaobab2020/solver/Iterator1.py
hackathonbaobab2020/solver/Milp1.py
hackathonbaobab2020/solver/__init__.py
hackathonbaobab2020/solver/algorithm1.py
hackathonbaobab2020/solver/brute_solver.py
hackathonbaobab2020/solver/cp_ortools.py
hackathonbaobab2020/solver/fix_loop_solver.py
hackathonbaobab2020/solver/loop_solver.py
hackathonbaobab2020/solver/milp_LP_HL/__init__.py
hackathonbaobab2020/solver/milp_LP_HL/configuration.py
hackathonbaobab2020/solver/milp_LP_HL/function_utils.py
hackathonbaobab2020/solver/milp_LP_HL/generic_iterator.py
hackathonbaobab2020/solver/milp_LP_HL/model.py
hackathonbaobab2020/solver/milp_LP_HL/project_utils.py
hackathonbaobab2020/solver/milp_LP_HL/pyomo_utils.py
hackathonbaobab2020/solver/milp_LP_HL/resources_subproblem.py
hackathonbaobab2020/tests/__init__.py
hackathonbaobab2020/tests/tests.py
hackathonbaobab2020-1.0.4.dist-info/LICENSE
hackathonbaobab2020-1.0.4.dist-info/METADATA
hackathonbaobab2020-1.0.4.dist-info/WHEEL
hackathonbaobab2020-1.0.4.dist-info/top_level.txt
hackathonbaobab2020-1.0.4.dist-info/RECORD
