Metadata-Version: 2.1
Name: hackathonbaobab2020
Version: 1.0.4
Summary: Hackathon 2020 at baobab soluciones
Home-page: https://github.com/baobabsoluciones/hackathonbaobab2020
Author: Franco Peschiera
Author-email: pchtsp@gmail.com
Maintainer: Franco Peschiera
Maintainer-email: pchtsp@gmail.com
License: UNKNOWN
Download-URL: https://github.com/baobabsoluciones/hackathonbaobab2020/archive/main.zip
Keywords: math hackathon pulp ortools pyomo
Platform: UNKNOWN
Classifier: Programming Language :: Python :: 3
Classifier: License :: OSI Approved :: MIT License
Classifier: Operating System :: OS Independent
Requires-Dist: click
Requires-Dist: pandas
Requires-Dist: orloge
Requires-Dist: cornflow-client
Provides-Extra: benchmark
Requires-Dist: tabulate; extra == "benchmark"
Requires-Dist: pygount; extra == "benchmark"
Requires-Dist: plotly; extra == "benchmark"
Requires-Dist: seaborn; extra == "benchmark"
Provides-Extra: solvers
Requires-Dist: pyomo; extra == "solvers"
Requires-Dist: ortools; extra == "solvers"
